Workbook

Sheet Resumen
B2: HUB Digital IHP
B3: Costos de infraestructura en la nube (Azure) - resumen ejecutivo
B4: Region: Mexico Central | Moneda: USD | Precios base de lista (sin IVA)
B6: VERSION DE AHORRO (1 local) | D6: CONFIGURACION NORMAL (2 locales)
B7: =Servicios!H15 | D7: =Servicios!J15
B8: Lo minimo para operar: un solo App Service compartido. Asi se arranca pagando menos. | D8: La que normalmente se cotiza: recepcion en su propio local. Mas estable y segura.
B10: Diferencia = el 2o local (App Service) | C10: =Servicios!J15-Servicios!H15
B12: Desglose (configuracion normal, 2 locales)
B13: Servicio | C13: USD/mes
B14: =Servicios!B5 | C14: =Servicios!J5
B15: =Servicios!B6 | C15: =Servicios!J6
B16: =Servicios!B7 | C16: =Servicios!J7
B17: =Servicios!B8 | C17: =Servicios!J8
B18: =Servicios!B9 | C18: =Servicios!J9
B19: =Servicios!B10 | C19: =Servicios!J10
B20: =Servicios!B11 | C20: =Servicios!J11
B21: =Servicios!B12 | C21: =Servicios!J12
B22: =Servicios!B13 | C22: =Servicios!J13
B23: =Servicios!B14 | C23: =Servicios!J14
B24: TOTAL normal | C24: =Servicios!J15
B26: Nota: precios base. Con trafico real (visitas, descargas, monitoreo) la factura sube. Ver hoja 'A considerar'.

Sheet Servicios
A1: HUB Digital IHP - Que rentamos en la nube (Azure)
A2: Precios base aproximados de lista, USD/mes, region Mexico Central. Editables: cambia la columna 'Precio unit.' y los totales se recalculan.
A4: # | B4: Servicio (en simple) | C4: Producto Azure | D4: Para que sirve | E4: Que rentamos (config minima) | F4: Precio unit. (USD/mes) | G4: Cant. 1 local | H4: Subtotal ahorro | I4: Cant. 2 locales | J4: Subtotal normal | K4: Como se paga | L4: A considerar
A5: 1 | B5: El local de las apps | C5: Azure App Service (Plan P1v3 Linux) | D5: Mantiene encendidos los programas (recepcion y 3 areas) las 24 horas. | E5: 1 plan al inicio; 2 recomendado (recepcion aparte) | F5: 120 | G5: 1 | H5: =F5*G5 | I5: 2 | J5: =F5*I5 | K5: Fijo mensual | L5: Pieza mas cara. Es el minimo que soporta red privada (no baja de P1v3). Se puede reservar 1-3 anos (-30% a -55%). El 2o local es el salto de costo mas grande.
A6: 2 | B6: Memoria rapida | C6: Azure Cache for Redis (Standard C1, 1 GB) | D6: Acelera la plataforma y guarda las sesiones de usuario. | E6: Standard C1 (con replica de respaldo) | F6: 100 | G6: 1 | H6: =F6*G6 | I6: 1 | J6: =F6*I6 | K6: Fijo mensual | L6: 2a mas cara. Standard incluye replica y garantia (SLA). Existe Basic C1 (~$40) sin respaldo si se busca ahorrar.
A7: 3 | B7: La entrada | C7: Azure Front Door (Standard) | D7: Puerta unica al publico: filtra, protege y acelera las visitas. | E7: Plan Standard | F7: 35 | G7: 1 | H7: =F7*G7 | I7: 1 | J7: =F7*I7 | K7: Base + uso | L7: Cobra base mensual + visitas + datos transferidos. Premium (con firewall WAF) cuesta desde ~$300/mes.
A8: 4 | B8: El archivero | C8: Azure Database for PostgreSQL (Flexible B1ms) | D8: Guarda de forma permanente usuarios, cursos, publicaciones y reportes. | E8: Tamano economico (Burstable) + 32 GB | F8: 15 | G8: 1 | H8: =F8*G8 | I8: 1 | J8: =F8*I8 | K8: Base + almacen | L8: Compute ~$12 + 32 GB de espacio. Respaldo de 7 dias incluido. Sube si se agranda el servidor o el espacio.
A9: 5 | B9: El sitio web | C9: Azure Static Web Apps (Standard) | D9: La cara visible: pantallas y botones que usa la gente. | E9: Plan Standard (dominio propio + HTTPS) | F9: 9 | G9: 1 | H9: =F9*G9 | I9: 1 | J9: =F9*I9 | K9: Fijo mensual | L9: Se cobra por aplicacion. Incluye certificado de seguridad (HTTPS) sin costo extra.
A10: 6 | B10: La bodega de archivos | C10: Azure Storage (Standard LRS) | D10: Guarda fotos, videos y documentos que sube la gente. | E10: Almacenamiento estandar | F10: 5 | G10: 1 | H10: =F10*G10 | I10: 1 | J10: =F10*I10 | K10: Por uso | L10: Se paga por GB y por operaciones. Arranca barato y sube con cuanto suba la gente.
A11: 7 | B11: Cajas de instalacion | C11: Azure Container Registry (Basic) | D11: Guarda las versiones listas de cada programa para instalarlas igual siempre. | E11: Plan Basic | F11: 5 | G11: 1 | H11: =F11*G11 | I11: 1 | J11: =F11*I11 | K11: Fijo mensual | L11: Basic alcanza al inicio. Premium solo si se exige red privada del registro.
A12: 8 | B12: Caja fuerte de claves | C12: Azure Key Vault (Standard) | D12: Resguarda contrasenas y llaves; nadie las escribe en el codigo. | E12: Estandar (por operacion) | F12: 1 | G12: 1 | H12: =F12*G12 | I12: 1 | J12: =F12*I12 | K12: Por uso | L12: Costo casi nulo: se cobra por operacion (centavos).
A13: 9 | B13: Camaras y monitoreo | C13: App Insights + Log Analytics | D13: Vigilan que todo funcione y avisan si algo falla. | E13: Por GB de registros | F13: 5 | G13: 1 | H13: =F13*G13 | I13: 1 | J13: =F13*I13 | K13: Por uso | L13: Se paga por GB de logs ingeridos. Sube con el trafico y el nivel de diagnostico.
A14: 10 | B14: Pasillos privados e identidades | C14: VNet + Managed Identity + DNS privado | D14: Comunican las areas por dentro, de forma cerrada y segura. | E14: Incluido en el diseno | F14: 0 | G14: 1 | H14: =F14*G14 | I14: 1 | J14: =F14*I14 | K14: Incluido | L14: La red y las identidades no tienen costo. El DNS privado son centavos. En modo 'max' se agregan Private Endpoints (~$7/mes c/u).
B15: TOTAL (USD/mes) | H15: =SUM(H5:H14) | J15: =SUM(J5:J14)
B17: Version de ahorro = 1 local (App Service). Configuracion normal = 2 locales (la que normalmente se cotiza).

Sheet A considerar
B2: Cosas a considerar antes de contratar
B3: Lo que puede mover el costo hacia arriba o abajo respecto a las cifras base.
B5: Tema | C5: Que tener en cuenta
B6: 1 local vs 2 locales | C6: El salto mas grande de costo. 1 local (~ahorro) comparte todo; 2 locales (~normal) separa la recepcion. Es +1 App Service (~$120/mes).
B7: Son precios base, no la factura | C7: Las cifras son el piso de lista. La factura real sube con el uso: visitas, descargas, logs y transferencia de datos.
B8: Transferencia de datos (egress) | C8: Sacar datos de Azure hacia internet se cobra. Con poco trafico es bajo; con video/descargas masivas crece.
B9: Monitoreo (logs) | C9: App Insights y Log Analytics cobran por GB de registros. A mas trafico o mas detalle de diagnostico, mas costo.
B10: Almacenamiento que crece | C10: Storage y la base de datos crecen con el uso (fotos, videos, expedientes). Se paga por lo que se ocupa.
B11: Redis: Standard vs Basic | C11: Standard C1 (~$100) trae replica y garantia (SLA). Basic C1 (~$40) es mas barato pero sin respaldo: si se reinicia, se pierde la cache.
B12: Descuentos por reserva | C12: Comprometer 1 o 3 anos en App Service baja el costo hasta 30%-55%. Util cuando el uso ya es estable.
B13: Precios Dev/Test | C13: Entornos de prueba pueden usar tarifas Dev/Test mas baratas (no para produccion).
B14: Front Door: base + uso | C14: Standard cobra una base (~$35) mas requests y datos. Premium (con firewall WAF) sube a ~$300+/mes.
B15: Modo de red 'max' | C15: Si se exige aislamiento total, se agregan Private Endpoints (~$7/mes cada uno) y mas zonas DNS. Sube el total.
B16: Media privada (Premium) | C16: Servir archivos de forma privada usa Front Door Premium + storage privado: agrega varios cientos de USD/mes.
... B19: Lo que NO cuesta extra | C19: Red privada (VNet), identidades y certificados HTTPS vienen incluidos en el diseno.
